autocpd/__init__.py
autocpd/neuralnetwork.py
autocpd/pre_trained_model.py
autocpd/utils.py
autocpd/Demo/confusion_matrix.npy
autocpd/Demo/label_dict.npy
autocpd/Demo/model/keras_metadata.pb
autocpd/Demo/model/saved_model.pb
autocpd/Demo/model/variables/variables.data-00000-of-00001
autocpd/Demo/model/variables/variables.index
autocpd/Demo/train/events.out.tfevents.1650019438.icarus-phys-cpu-1-4.kent.ac.uk.18505.0.v2
autocpd/Demo/train/events.out.tfevents.1650019603.icarus-phys-cpu-1-0.kent.ac.uk.6486.0.v2
autocpd/Demo/train/events.out.tfevents.1650021291.icarus-phys-gpu-0-1.kent.ac.uk.10010.0.v2
autocpd/Demo/validation/events.out.tfevents.1650019509.icarus-phys-cpu-1-4.kent.ac.uk.18505.1.v2
autocpd/Demo/validation/events.out.tfevents.1650019674.icarus-phys-cpu-1-0.kent.ac.uk.6486.1.v2
autocpd/Demo/validation/events.out.tfevents.1650021304.icarus-phys-gpu-0-1.kent.ac.uk.10010.1.v2
autocpd/HASC/person101/HASC1001-acc.csv
autocpd/HASC/person101/HASC1001.label
autocpd/HASC/person101/HASC1001.meta
autocpd/HASC/person101/HASC1002-acc.csv
autocpd/HASC/person101/HASC1002.label
autocpd/HASC/person101/HASC1002.meta
autocpd/HASC/person102/HASC1003-acc.csv
autocpd/HASC/person102/HASC1003.label
autocpd/HASC/person102/HASC1003.meta
autocpd/HASC/person102/HASC1004-acc.csv
autocpd/HASC/person102/HASC1004.label
autocpd/HASC/person102/HASC1004.meta
autocpd/HASC/person102/HASC1005-acc.csv
autocpd/HASC/person102/HASC1005.label
autocpd/HASC/person102/HASC1005.meta
autocpd/HASC/person103/HASC1006-acc.csv
autocpd/HASC/person103/HASC1006.label
autocpd/HASC/person103/HASC1006.meta
autocpd/HASC/person103/HASC1007-acc.csv
autocpd/HASC/person103/HASC1007.label
autocpd/HASC/person103/HASC1007.meta
autocpd/HASC/person104/HASC1008-acc.csv
autocpd/HASC/person104/HASC1008.label
autocpd/HASC/person104/HASC1008.meta
autocpd/HASC/person104/HASC1009-acc.csv
autocpd/HASC/person104/HASC1009.label
autocpd/HASC/person104/HASC1009.meta
autocpd/HASC/person105/HASC1010-acc.csv
autocpd-0.1.5.dist-info/METADATA
autocpd-0.1.5.dist-info/WHEEL
autocpd-0.1.5.dist-info/licenses/LICENSE.txt
autocpd-0.1.5.dist-info/RECORD
