Metadata-Version: 2.1
Name: autocpd
Version: 0.1.5
Summary: The implementation of algorithm in AutoCPD
Project-URL: Homepage, https://github.com/Jieli12/AutoCPD
Project-URL: Documentation, https://autocpd.readthedocs.io/en/latest/
Project-URL: Bug Tracker, https://github.com/Jieli12/AutoCPD/issues
Author-email: "Jie Li, et al." <j.li196@lse.ac.uk>, Paul Fearnhead <p.fearnhead@lancaster.ac.uk>, Piotr Fryzlewicz <p.fryzlewicz@lse.ac.uk>, Tengyao Wang <t.wang59@lse.ac.uk>
Maintainer-email: Jie Li <j.li196@lse.ac.uk>
License-File: LICENSE.txt
Classifier: License :: OSI Approved :: MIT License
Classifier: Operating System :: OS Independent
Classifier: Programming Language :: Python :: 3
Requires-Python: >=3.9
Requires-Dist: matplotlib
Requires-Dist: numpy
Requires-Dist: pandas
Requires-Dist: scikit-learn
Requires-Dist: scipy
Requires-Dist: statsmodels
